{
    "version": "2.0",
	"brandName": "ADN",
	"brandId": "31",
	"sectionName": "Algemeen",
	"sectionId": "268",
    "genreId": "nieuws staand",
    "shapeTypeName": "secondary",
    "shapeTypeId": "2",
    "geometricBounds": {
        "x": 1306.619,
        "y": 80.85,
        "width": 141.809,
        "height": 759
    },
    "foldLine": null,
    "textComponents": [
        {
            "type": "KOP",
            "words": 6,
            "characters": 29,
            "firstParagraphStyle": "KOPP_0113 Haas Black 24",
            "oversetLines": 0,
            "visibleArea": 10913.33,
            "requiredVisibleArea": 10913.33,
            "frames": [
                {
                    "id": 277971,
                    "geometricBounds": {
                        "x": 0.076,
                        "y": 22,
                        "width": 141.732,
                        "height": 77
                    },
                    "columns": 1,
                    "words": 6,
                    "characters": 29,
                    "textWrapMode": "none",
                    "zIndex": 547,
                    "locked": false,
                    "text": "Nws 1 kolVid rendem et (1000)"
                }
            ]
        },
        {
            "type": "INTRO",
            "words": 33,
            "characters": 196,
            "firstParagraphStyle": "INTR_0004 Tekst Lead",
            "oversetLines": 0,
            "visibleArea": 10999.372,
            "requiredVisibleArea": 10999.372,
            "frames": [
                {
                    "id": 278097,
                    "geometricBounds": {
                        "x": 0.076,
                        "y": 109.351,
                        "width": 141.656,
                        "height": 77.649
                    },
                    "columns": 1,
                    "words": 33,
                    "characters": 196,
                    "textWrapMode": "bounding_box",
                    "zIndex": 559,
                    "locked": false,
                    "text": "Intr_0004 klein, vet, cursief Groei Het Algemeen Dagblad of AD is een Nederlands landelijk dagblad en met een oplage in 2013 van ruim 409 duizend exemplaren de op één na grootste betaalde krant ",
                    "textWrapOffset": {
                        "top": 0,
                        "left": 0,
                        "bottom": 11.339,
                        "right": 0
                    }
                }
            ]
        },
        {
            "type": "AUTEUR",
            "words": 2,
            "characters": 18,
            "firstParagraphStyle": "AUTE_0005 Auteur",
            "oversetLines": 0,
            "visibleArea": 2537.642,
            "requiredVisibleArea": 2537.642,
            "frames": [
                {
                    "id": 278071,
                    "geometricBounds": {
                        "x": 0.076,
                        "y": 186.351,
                        "width": 141.732,
                        "height": 29.886
                    },
                    "columns": 1,
                    "words": 2,
                    "characters": 18,
                    "textWrapMode": "bounding_box",
                    "zIndex": 557,
                    "locked": false,
                    "text": "AUTE_0005 Auteur  ",
                    "textWrapOffset": {
                        "top": 0,
                        "left": 0,
                        "bottom": 0,
                        "right": 0
                    }
                }
            ]
        },
        {
            "type": "PLAATS",
            "words": 2,
            "characters": 16,
            "firstParagraphStyle": "PLAA_0006 Plaats",
            "oversetLines": 0,
            "visibleArea": 948.014,
            "requiredVisibleArea": 948.014,
            "frames": [
                {
                    "id": 278046,
                    "geometricBounds": {
                        "x": 0.229,
                        "y": 205.351,
                        "width": 141.579,
                        "height": 17.582
                    },
                    "columns": 1,
                    "words": 2,
                    "characters": 16,
                    "textWrapMode": "bounding_box",
                    "zIndex": 555,
                    "locked": false,
                    "text": "PLAA_0006 Plaats",
                    "textWrapOffset": {
                        "top": 0,
                        "left": 0,
                        "bottom": 2.835,
                        "right": 0
                    }
                }
            ]
        },
        {
            "type": "TEKST",
            "words": 127,
			"characters": 1000,
            "firstParagraphStyle": "TKSX_0001a Tekst Niet inspringen",
            "oversetLines": 1,
            "visibleArea": 42837.49,
            "requiredVisibleArea": 43383.16,
            "frames": [
                {
                    "id": 277995,
                    "geometricBounds": {
                        "x": 0.076,
                        "y": 201.294,
                        "width": 141.732,
                        "height": 326.706
                    },
                    "columns": 1,
                    "words": 127,
                    "characters": 788,
                    "textWrapMode": "none",
                    "zIndex": 549,
                    "locked": false,
                    "text": "TKSX_0001a vet cursief cuve\rTKST_0000 vet cursief cuve\rTKOP_0031 NWS\rVRAA_0001 cursief cuve\rANTW_0002 vet cursief cuve\rTKST Het Algemeen Dagblad profileert zich sinds zijn oprichting als een neutrale krant zonder politieke of religieuze binding. Volgens het redactiestatuut dient de krant een populair, betrouwbaar, onafhankelijk landelijk ochtendblad te zijn. Sinds de overname door De Persgroep is de signatuur gelijk aan die van zijn Belgische evenknie Het Laatste Nieuws die links progressief liberaal is. Hoewel het Algemeen Dagblad als landelijke krant overal verkrijgbaar is, wordt de krant het meest gelezen in het zuidwesten van Nederland. Een kwart van de abonnees woont in de drie grote steden in het westen van het land. De krant werd in 1946 als zusje van de Nieuwe Rotterdam"
                }
            ]
        },
        {
            "type": "BIJSCHRIFT",
            "words": 1,
            "characters": 10,
            "firstParagraphStyle": "BIJS_0302 Bijschrift BOVEN",
            "oversetLines": 0,
            "visibleArea": 3118.11,
            "requiredVisibleArea": 3118.11,
            "frames": [
                {
                    "id": 278019,
                    "geometricBounds": {
                        "x": 0.076,
                        "y": 737,
                        "width": 141.732,
                        "height": 22
                    },
                    "columns": 1,
                    "words": 1,
                    "characters": 10,
                    "textWrapMode": "bounding_box",
                    "zIndex": 551,
                    "locked": false,
                    "text": "Bijschrift",
                    "textWrapOffset": {
                        "top": 0,
                        "left": 0,
                        "bottom": 5.669,
                        "right": 0
                    }
                }
            ]
        }
    ],
    "imageComponents": [
        {
            "id": 278044,
            "geometricBounds": {
                "x": 0.076,
                "y": 539,
                "width": 141.732,
                "height": 190.929
            },
            "textWrapMode": "bounding_box",
            "zIndex": 553,
            "locked": false,
            "textWrapOffset": {
                "top": 0,
                "left": 0,
                "bottom": 0,
                "right": 0
            }
        }
    ]
}