{
    "version": "2.0",
	"brandName": "ADN",
	"brandId": "31",
	"sectionName": "Regio",
	"sectionId": "255",
    "genreId": "lees",
    "shapeTypeName": "lead",
    "shapeTypeId": "1",
    "geometricBounds": {
        "x": 847.559,
        "y": 80.85,
        "width": 600.945,
        "height": 496.291
    },
    "foldLine": null,
    "textComponents": [
        {
            "type": "BOVENKOP",
            "words": 1,
            "characters": 8,
            "firstParagraphStyle": "BKOP_0151 Bovenkop Lijn Grijs",
            "oversetLines": 0,
            "visibleArea": 6485.669,
            "requiredVisibleArea": 6485.669,
            "frames": [
                {
                    "id": 275493,
                    "geometricBounds": {
                        "x": 0,
                        "y": 22,
                        "width": 589.606,
                        "height": 22
                    },
                    "columns": 1,
                    "words": 1,
                    "characters": 8,
                    "textWrapMode": "none",
                    "zIndex": 291,
                    "locked": false,
                    "text": "Bovenkop"
                }
            ]
        },
        {
            "type": "KOP",
            "words": 5,
            "characters": 22,
            "firstParagraphStyle": "KOPP_0106 Tiempos Light 51",
            "oversetLines": 0,
            "visibleArea": 4151.662,
            "requiredVisibleArea": 4151.662,
            "frames": [
                {
                    "id": 275517,
                    "geometricBounds": {
                        "x": 0,
                        "y": 55,
                        "width": 589.606,
                        "height": 44
                    },
                    "columns": 1,
                    "words": 5,
                    "characters": 22,
                    "textWrapMode": "none",
                    "zIndex": 292,
                    "locked": false,
                    "text": "Lees 4 kol 2600 tekens"
                }
            ]
        },
        {
            "type": "PLAATS",
            "words": 2,
            "characters": 16,
            "firstParagraphStyle": "PLAA_0006 Plaats",
            "oversetLines": 0,
            "visibleArea": 0,
            "requiredVisibleArea": 0,
            "frames": [
                {
                    "id": 291632,
                    "geometricBounds": {
                        "x": 0.153,
                        "y": 217,
                        "width": 141.579,
                        "height": 27.933
                    },
                    "columns": 1,
                    "words": 2,
                    "characters": 16,
                    "textWrapMode": "bounding_box",
                    "zIndex": 300,
                    "locked": false,
                    "text": "PLAA_0006 Plaats",
                    "textWrapOffset": {
                        "top": 0,
                        "left": 0,
                        "bottom": 2.835,
                        "right": 0
                    }
                }
            ]
        },
        {
            "type": "AUTEUR",
            "words": 2,
            "characters": 18,
            "firstParagraphStyle": "AUTE_0005 Auteur",
            "oversetLines": 0,
            "visibleArea": 0,
            "requiredVisibleArea": 0,
            "frames": [
                {
                    "id": 291658,
                    "geometricBounds": {
                        "x": 0,
                        "y": 198,
                        "width": 141.732,
                        "height": 40.237
                    },
                    "columns": 1,
                    "words": 2,
                    "characters": 18,
                    "textWrapMode": "bounding_box",
                    "zIndex": 301,
                    "locked": false,
                    "text": "AUTE_0005 Auteur  ",
                    "textWrapOffset": {
                        "top": 0,
                        "left": 0,
                        "bottom": 0,
                        "right": 0
                    }
                }
            ]
        },
        {
            "type": "INTRO",
            "words": 36,
            "characters": 221,
            "firstParagraphStyle": "INTR_0202 Klein",
            "oversetLines": 0,
            "visibleArea": 0,
            "requiredVisibleArea": 0,
            "frames": [
                {
                    "id": 291683,
                    "geometricBounds": {
                        "x": 0,
                        "y": 110,
                        "width": 141.656,
                        "height": 102.865
                    },
                    "columns": 1,
                    "words": 36,
                    "characters": 221,
                    "textWrapMode": "bounding_box",
                    "zIndex": 302,
                    "locked": false,
                    "text": "Intr_0202 klein, vet, cursief Het Algemeen Dagblad of AD is een Nederlands landelijk dagblad en met een oplage in 2013 van ruim 409 duizend exemplaren de op één na grootste betaalde krant van Nederland. Krant verschijnt",
                    "textWrapOffset": {
                        "top": 0,
                        "left": 0,
                        "bottom": 11.339,
                        "right": 0
                    }
                }
            ]
        },
        {
            "type": "TEKST",
            "words": 378,
			"characters": 2600,
            "firstParagraphStyle": "TKSX_0003a Tekst RR Niet inspringen",
            "oversetLines": 1,
            "visibleArea": 23281.938,
            "requiredVisibleArea": 27301.005,
            "frames": [
                {
                    "id": 275541,
                    "geometricBounds": {
                        "x": 0,
                        "y": 110,
                        "width": 589.606,
                        "height": 386.291
                    },
                    "columns": 4,
                    "words": 378,
                    "characters": 2303,
                    "textWrapMode": "none",
                    "zIndex": 293,
                    "locked": false,
                    "text": "TKSX_0003a vet cursief vetcurs\rTKST_0002 vet cursief vetcurs\rTKOP_0032 RR\rVRAA_0001 Tekst v c cuve\rANTW_0002 Tekst v c cuve\rTKSTHet Algemeen Dagblad profileert zich sinds zijn oprichting als een neutrale krant zonder politieke of religieuze binding. Volgens het redactiestatuut dient de krant ‘een populair, betrouwbaar, onafhankelijk landelijk ochtendblad’ te zijn. Sinds de overname door De Persgroep is de signatuur gelijk aan die van zijn Belgische evenknie Het Laatste Nieuws die links progressief liberaal is. Hoewel het Algemeen Dagblad als landelijke krant overal verkrijgbaar is, wordt de krant het meest gelezen in het zuidwesten van Nederland. Een kwart van de abonnees woont in de drie grote steden in het westen van het land.\rDe krant werd in 1946 als zusje van de Nieuwe Rotterdamsche Courant opgericht door W. Pluygers en J. Versnel. Pluygers werd de uitgever, Jan Schraver de eerste hoofdredacteur. Het eerste nummer verscheen op 29 april 1946. In 1964 werd de krant, die tot dan toe was uitgegeven door de Nieuwe Rotterdamsche Courant NV, overgenomen door de Nederlandse Dagblad Unie (NDU), ontstaan uit het samengaan van de NRC met het Algemeen Handelsblad. In 1979 fuseerde de NDU met uitgeverij Elsevier, die de dagbladpoot in 1995 afstootte naar PCM Uitgevers, waar Het Parool, Trouw en de Volkskrant al werden uitgegeven. PCM verwierf niet alleen het Algemeen Dagblad, maar ook de fusiekrant NRC Handelsblad. Het nieuwe AD is ondergebracht in [300] een joint venture waarin de uitgevers PCM en Wegener participeren. Lange tijd was het Algemeen Dagblad, na De Telegraaf, de tweede krant van Nederland. \rVanaf eind jaren tachtig verloor de krant lezers. Dat proces werd vanaf 1993 versterkt door de abrupte koerswijziging van toenmalig hoofdredacteur Peter van Dijk, die de krant een volledig nieuw uiterlijk gaf en van het dagblad een kwaliteitskrant wilde maken. Veel lezers waren daar niet van gediend. De overname van NDU door PCM frustreerde Van Dijks plannen enigszins, omdat het niet in het belang van het bedrijf was dat het Algemeen Dagblad zou concurreren met de Volkskrant, die toen erg succesvol was. Na een kort hoofdredacteurschap van Oscar Garschagen, die de titel op de voorpagina voorzag van ‘Nederlands populairste kwaliteitskrant’, werd ombudsman Willem Am"
                }
            ]
        },
        {
            "type": "QUOTE",
            "words": 5,
            "characters": 24,
            "firstParagraphStyle": "QUOT_0403 Bewering",
            "oversetLines": 0,
            "visibleArea": 9167.244,
            "requiredVisibleArea": 9167.244,
            "frames": [
                {
                    "id": 286297,
                    "geometricBounds": {
                        "x": 300.472,
                        "y": 429,
                        "width": 138.898,
                        "height": 66
                    },
                    "columns": 1,
                    "words": 5,
                    "characters": 24,
                    "textWrapMode": "bounding_box",
                    "zIndex": 299,
                    "locked": false,
                    "text": "Bewering\n2\n3\n4 regeltjes",
                    "textWrapOffset": {
                        "top": 2.835,
                        "left": 0,
                        "bottom": 5.669,
                        "right": 0
                    }
                }
            ]
        },
        {
            "type": "BIJSCHRIFT",
            "words": 1,
            "characters": 11,
            "firstParagraphStyle": "BIJS_0302 Bijschrift BOVEN",
            "oversetLines": 1,
            "visibleArea": 0,
            "requiredVisibleArea": 0,
            "frames": [
                {
                    "id": 275568,
                    "geometricBounds": {
                        "x": 150.236,
                        "y": 319,
                        "width": 289.187,
                        "height": 11
                    },
                    "columns": 1,
                    "words": 1,
                    "characters": 11,
                    "textWrapMode": "bounding_box",
                    "zIndex": 294,
                    "locked": false,
                    "text": "Bijschrift.",
                    "textWrapOffset": {
                        "top": 0,
                        "left": 0,
                        "bottom": 5.669,
                        "right": 0
                    }
                }
            ]
        }
    ],
    "imageComponents": [
        {
            "id": 275593,
            "geometricBounds": {
                "x": 150.236,
                "y": 114,
                "width": 289.187,
                "height": 199
            },
            "textWrapMode": "bounding_box",
            "zIndex": 295,
            "locked": false,
            "textWrapOffset": {
                "top": 0,
                "left": 0,
                "bottom": 5.5,
                "right": 0
            }
        }
    ]
}